thumbor_plugins/__init__.py
thumbor_plugins/optimizers/__init__.py
thumbor_plugins/optimizers/auto.py
thumbor_plugins/optimizers/jp2.py
thumbor_plugins/optimizers/jpegrecompress.py
thumbor_plugins/optimizers/mozjpeg.py
thumbor_plugins/optimizers/optipng.py
thumbor_plugins/optimizers/pngcrush.py
thumbor_plugins/optimizers/pngquant.py
thumbor_plugins-0.2.4.dist-info/LICENSE
thumbor_plugins-0.2.4.dist-info/METADATA
thumbor_plugins-0.2.4.dist-info/WHEEL
thumbor_plugins-0.2.4.dist-info/top_level.txt
thumbor_plugins-0.2.4.dist-info/RECORD
